easybuilder-0.2.1.dist-info/METADATA
easybuilder-0.2.1.dist-info/WHEEL
easybuilder-0.2.1.dist-info/entry_points.txt
easybuilder/__init__.py
easybuilder/builder.py
easybuilder/checker.py
easybuilder/task/__init__.py
easybuilder/temputils.py
easybuilder/worker.py
easybuilder-0.2.1.dist-info/RECORD
