Metadata-Version: 2.1
Name: easybuilder
Version: 0.2.1
Summary: Default template for PDM package
Author-Email: svtter <svtter@qq.com>
License: MIT
Requires-Python: >=3.9
Requires-Dist: loguru>=0.7.2
